ml_tooling/__init__.py
ml_tooling/almbrand.mplstyle
ml_tooling/baseclass.py
ml_tooling/config.py
ml_tooling/utils.py
ml_tooling/data/__init__.py
ml_tooling/data/base_data.py
ml_tooling/data/file.py
ml_tooling/data/load_demo.py
ml_tooling/data/sql.py
ml_tooling/logging/__init__.py
ml_tooling/logging/log_estimator.py
ml_tooling/logging/logger.py
ml_tooling/metrics/__init__.py
ml_tooling/metrics/confusion_matrix.py
ml_tooling/metrics/correlation.py
ml_tooling/metrics/lift_score.py
ml_tooling/metrics/metric.py
ml_tooling/metrics/utils.py
ml_tooling/plots/__init__.py
ml_tooling/plots/confusion_matrix.py
ml_tooling/plots/correlation.py
ml_tooling/plots/feature_importance.py
ml_tooling/plots/learning_curve.py
ml_tooling/plots/lift_curve.py
ml_tooling/plots/missing_data.py
ml_tooling/plots/permutation_importance.py
ml_tooling/plots/precision_recall_curve.py
ml_tooling/plots/prediction_error.py
ml_tooling/plots/residuals.py
ml_tooling/plots/roc_auc.py
ml_tooling/plots/target_feature_distribution.py
ml_tooling/plots/utils.py
ml_tooling/plots/validation_curve.py
ml_tooling/plots/viz/__init__.py
ml_tooling/plots/viz/baseviz.py
ml_tooling/plots/viz/classification_viz.py
ml_tooling/plots/viz/data_viz.py
ml_tooling/plots/viz/regression_viz.py
ml_tooling/result/__init__.py
ml_tooling/result/result.py
ml_tooling/result/result_group.py
ml_tooling/search/__init__.py
ml_tooling/search/base.py
ml_tooling/search/bayes.py
ml_tooling/search/gridsearch.py
ml_tooling/search/randomsearch.py
ml_tooling/storage/__init__.py
ml_tooling/storage/artifactory.py
ml_tooling/storage/base.py
ml_tooling/storage/file.py
ml_tooling/transformers/__init__.py
ml_tooling/transformers/binarize.py
ml_tooling/transformers/binner.py
ml_tooling/transformers/date_encoder.py
ml_tooling/transformers/feature_union.py
ml_tooling/transformers/fillna.py
ml_tooling/transformers/freqfeature.py
ml_tooling/transformers/functransform.py
ml_tooling/transformers/pipeline.py
ml_tooling/transformers/rare_feature.py
ml_tooling-0.12.1.dist-info/METADATA
ml_tooling-0.12.1.dist-info/WHEEL
ml_tooling-0.12.1.dist-info/licenses/LICENSE
ml_tooling-0.12.1.dist-info/RECORD
