Metadata-Version: 2.1
Name: ml-tooling
Version: 0.12.1
Summary: A library for machine learning utilities
Project-URL: Bug Tracker, https://github.com/andersbogsnes/ml_tooling/issues
Project-URL: Documentation, https://ml-tooling.readthedocs.io/en/stable/
Project-URL: Homepage, https://github.com/andersbogsnes/ml_tooling
Project-URL: Source Code, https://github.com/andersbogsnes/ml_tooling
Author-email: Anders Bogsnes <andersbogsnes@gmail.com>
Keywords: framework,ml,tooling
Classifier: Development Status :: 3 - Alpha
Classifier: Intended Audience :: Developers
Classifier: License :: OSI Approved :: MIT License
Classifier: Operating System :: OS Independent
Classifier: Programming Language :: Python :: 3.7
Classifier: Programming Language :: Python :: 3.8
Classifier: Programming Language :: Python :: 3.9
Classifier: Programming Language :: Python :: 3.10
Classifier: Programming Language :: Python :: Implementation :: CPython
Requires-Python: >=3.7
Requires-Dist: attrs
Requires-Dist: joblib
Requires-Dist: matplotlib
Requires-Dist: pandas
Requires-Dist: pyyaml
Requires-Dist: scikit-learn
Requires-Dist: scikit-optimize
Requires-Dist: sqlalchemy
Provides-Extra: artifactory
Requires-Dist: dohq-artifactory; extra == 'artifactory'
Provides-Extra: dev
Requires-Dist: pre-commit; extra == 'dev'
Requires-Dist: pytest; extra == 'dev'
Requires-Dist: pytest-cov; extra == 'dev'
Requires-Dist: sphinx; extra == 'dev'
Requires-Dist: sphinx-rtd-theme; extra == 'dev'
Requires-Dist: tox; extra == 'dev'
Provides-Extra: docs
Requires-Dist: sphinx; extra == 'docs'
Requires-Dist: sphinx-rtd-theme; extra == 'docs'
Provides-Extra: tests
Requires-Dist: pytest; extra == 'tests'
Requires-Dist: pytest-cov; extra == 'tests'
